pirsadl/__init__.py
pirsadl/__main__.py
pirsa_dl-1.0.0.dist-info/LICENSE
pirsa_dl-1.0.0.dist-info/METADATA
pirsa_dl-1.0.0.dist-info/WHEEL
pirsa_dl-1.0.0.dist-info/dependency_links.txt
pirsa_dl-1.0.0.dist-info/entry_points.txt
pirsa_dl-1.0.0.dist-info/top_level.txt
pirsa_dl-1.0.0.dist-info/RECORD
